main.py
src/converter_package_Hugo/__init__.py
src/converter_package_Hugo/converter.py
converter_package_hugo_azix-0.0.1.dist-info/METADATA
converter_package_hugo_azix-0.0.1.dist-info/WHEEL
converter_package_hugo_azix-0.0.1.dist-info/licenses/LICENSE
converter_package_hugo_azix-0.0.1.dist-info/RECORD
